{
  "authors": [
    {"id": 1, "name": "Steve", "email": "steve@gmail.com"},
    {"id": 2, "name": "Hopper", "email": "jim@gmail.com"},
    {"id": 3, "name": "Robin", "email": "robin@gmail.com"}
  ],
  "recipients": [
    {"id": 1, "name": "Max", "email": "max@gmail.com"}, 
    {"id": 2, "name": "Lucas", "email": "lucas@gmail.com"},
    {"id": 3, "name": "Argyle", "email": "argyle@gmail.com"}
  ],
  "topics": [
    {"id": 1, "type": "Friendly"},
    {"id": 2, "type": "Timid"},
    {"id": 3, "type": "Scared"},
    {"id": 4, "type": "Overwhelmed"},
    {"id": 5, "type": "Chaos"}
  ],
  "posts": [
    {
      "id": 1,
      "title": "json-server",
      "author": "typicode"
    }
  ],
  "comments": [
    {
      "id": 1,
      "body": "some comment",
      "postId": 1
    }
  ],
  "profile": {
    "name": "typicode"
  }, 
  "sentLetters": []
}